pepotron/__init__.py
pepotron/__main__.py
pepotron/_cache.py
pepotron/_version.py
pepotron/cli.py
pepotron/scripts/__init__.py
pepotron/scripts/run_command.py
pepotron-1.5.0.dist-info/METADATA
pepotron-1.5.0.dist-info/WHEEL
pepotron-1.5.0.dist-info/entry_points.txt
pepotron-1.5.0.dist-info/licenses/LICENSE.txt
pepotron-1.5.0.dist-info/RECORD
