Metadata-Version: 2.4
Name: pepotron
Version: 1.5.0
Summary: CLI to open PEPs in your browser
Project-URL: Changelog, https://github.com/hugovk/pepotron/releases
Project-URL: Homepage, https://github.com/hugovk/pepotron
Project-URL: Source, https://github.com/hugovk/pepotron
Author: Hugo van Kemenade
License: MIT
License-File: LICENSE.txt
Keywords: bpo,cli,pep
Classifier: Development Status :: 5 - Production/Stable
Classifier: Intended Audience :: Developers
Classifier: Intended Audience :: End Users/Desktop
Classifier: License :: OSI Approved :: MIT License
Classifier: Operating System :: OS Independent
Classifier: Programming Language :: Python :: 3 :: Only
Classifier: Programming Language :: Python :: 3.9
Classifier: Programming Language :: Python :: 3.10
Classifier: Programming Language :: Python :: 3.11
Classifier: Programming Language :: Python :: 3.12
Classifier: Programming Language :: Python :: 3.13
Classifier: Programming Language :: Python :: 3.14
Classifier: Programming Language :: Python :: Implementation :: CPython
Classifier: Programming Language :: Python :: Implementation :: PyPy
Requires-Python: >=3.9
Requires-Dist: ghapi
Requires-Dist: platformdirs
Requires-Dist: python-slugify
Requires-Dist: rapidfuzz
Requires-Dist: urllib3>=2
Provides-Extra: tests
Requires-Dist: freezegun; extra == 'tests'
Requires-Dist: pytest; extra == 'tests'
Requires-Dist: pytest-cov; extra == 'tests'
